{
  "modid": "duelistmod",
  "name": "Duelist Mod",
  "author_list": ["Nyoxide"],
  "description": "A Slay the Spire adaptation of Yu-Gi-Oh!\nAdds 128 cards, 4 relics, 2 potions and new buff/debuff powers exclusively to the Duelist character.\n\nREQUIREMENTS\nBasemod, StSLib, Replay the Spire, Conspire, Spike's Relics, The Servant, Slimebound\n\nSOURCE\n https://github.com/adambennett/StS-DuelistMod \n\nPATCH NOTES\nv1.128.1\n- All cards should now properly respect Strength and Dexterity (for real)\n- Fixed Superheavy Brawler not tributing properly\n- Made sure Superheavy Swordsman and Superheavy Ogre do not target unless upgraded\n- Fixed Ookazi text\n- Fixed Shard of Greed triggering 3 turns after you play it\n- Added 1 new buff to large random buff pool\n- Changed 'Creative AI' random buff to only ever give 1 card\n- Fixed Gravity Axe crash\n- Various balance changes\n\nv1.128.0\n- Added 24 new cards\n- Strength and Dexterity are still probably not being applied correctly to many cards; will be fixed in next build\n\nv1.104.0\n- Fixed cards not being affected by strength properly\n- Fixed some cards not being affected by dexterity properly\n- Readded Harpie's Feather Duster\n- Added Big Castle Wall\n- Added block gain to several cards\n- Increased block gain on several cards\n- Reduced rarity of several block cards\n- Millennium Shield now gives 5 dexterity\n- Dark Hole now steals block instead of just removing it\n\nv1.102.0\nMade updates possible through mod launcher\n\nv0.102.1\n- General power fixes\n- Added 1 new power\n- Changed buff pool logic to allow for two sizes of buff pools for different cards to pull from\n\n\nThanks for playing the Duelist! Please let me know if you have any feedback or bug reports!\nEmail: nyoxidestsmods@gmail.com\nDiscord: Nyoxide#3464",
  "version": "1.128.1",
  "sts_version": "1-23-2019",
  "mts_version": "3.8.3",
  "credits": "Shoutout to Konami",
  "dependencies": ["basemod", "stslib" ],
  "update_json": "https://api.github.com/repos/adambennett/StS-DuelistMod/releases/latest"
}
